spectroscpy/SpectroscPy_tools.py
spectroscpy/SpectroscPy_wrapper.py
spectroscpy/__init__.py
spectroscpy/anharmonic.py
spectroscpy/cauchy.py
spectroscpy/dipole_invesigation.py
spectroscpy/get_spectroscopy.py
spectroscpy/hyperraman.py
spectroscpy/ir.py
spectroscpy/openrsp_tensor_reader.py
spectroscpy/parameters.py
spectroscpy/plotting_module.py
spectroscpy/raman.py
spectroscpy/resonance_checks.py
spectroscpy/transform_nc_to_nm.py
spectroscpy/vib_analysis.py
spectroscpy/tests/__init__.py
spectroscpy/tests/test_anharmonic.py
spectroscpy/tests/test_cauchy.py
spectroscpy/tests/test_get_spectroscopy.py
spectroscpy/tests/test_hyperraman.py
spectroscpy/tests/test_integration.py
spectroscpy/tests/test_ir.py
spectroscpy/tests/test_openrsp_tensor_reader.py
spectroscpy/tests/test_plotting_module.py
spectroscpy/tests/test_raman.py
spectroscpy/tests/test_resonance_checks.py
spectroscpy/tests/test_transform_nc_to_nm.py
spectroscpy/tests/test_vib_analysis.py
SpectroscPy-0.3.1.dist-info/COPYING.LESSER
SpectroscPy-0.3.1.dist-info/COPYING.txt
SpectroscPy-0.3.1.dist-info/METADATA
SpectroscPy-0.3.1.dist-info/WHEEL
SpectroscPy-0.3.1.dist-info/top_level.txt
SpectroscPy-0.3.1.dist-info/RECORD
