Metadata-Version: 2.1
Name: SpectroscPy
Version: 0.3.1
Summary: SpectroscPy: Python tools for spectroscopy.
Home-page: https://gitlab.com/kdu002/SpectroscPy
Author: Karen Oda Hjorth Minde Dundas, Magnus Ringholm, Yann Cornaton, Benedicte Ofstad
Author-email: karen.o.dundas@uit.no
License: GPLv3+
Platform: UNKNOWN
